[
  {
    "id": "7ac80516-328a-45a2-a042-9bd3599f6c77",
    "slug": "bacillus-thuringiensis",
    "label": "Bacillus thuringiensis",
    "title": "Біологічний інсектицид №1 у світі",
    "description": "Природна бактерія, яка знищує шкідників зсередини – личинки совки, молі та листокрутки перестають живитися протягом кількох годин після контакту. Діє точково: вражає тільки цільових шкідників, не чіпає бджіл, сонечок та інших корисних комах.\nПовністю розкладається в ґрунті без токсичних залишків.",
    "image_url": "/inside-bacillus.webp",
    "image_alt": "Bacillus thuringiensis",
    "accent_color": "",
    "is_active": true,
    "order": 0,
    "created_at": "2026-06-01T10:27:32.902539+00:00",
    "updated_at": "2026-06-01T10:27:32.902539+00:00"
  },
  {
    "id": "d1e19dd5-9870-462e-a940-7e549be02e11",
    "slug": "trichoderma",
    "label": "Trichoderma",
    "title": "Гриб-антагоніст для захисту ґрунту",
    "description": "Trichoderma пригнічує патогенні гриби (фузаріум, пітіум, ризоктонію) й одночасно стимулює ріст коренів. Виділяє ферменти, що розкладають органіку та підвищують доступність елементів живлення.",
    "image_url": "/inside-bacillus.webp",
    "image_alt": "Trichoderma",
    "accent_color": "",
    "is_active": true,
    "order": 1,
    "created_at": "2026-06-01T10:27:32.902539+00:00",
    "updated_at": "2026-06-01T10:27:32.902539+00:00"
  },
  {
    "id": "73bfd9c3-a2cb-4118-8b34-2695de425dde",
    "slug": "azotfiksuyuchi-bakterii",
    "label": "Азотфіксуючі бактерії",
    "title": "Азот без витрат на хімію",
    "description": "Бульбочкові й вільноживучі бактерії перетворюють атмосферний азот на доступну для рослин форму. Економить до 30% дози мінеральних добрив без втрати врожайності.",
    "image_url": "/inside-bacillus.webp",
    "image_alt": "Азотфіксуючі бактерії",
    "accent_color": "",
    "is_active": true,
    "order": 2,
    "created_at": "2026-06-01T10:27:32.902539+00:00",
    "updated_at": "2026-06-01T10:27:32.902539+00:00"
  },
  {
    "id": "d9b60714-b400-4ca3-ba8f-98ac42b93e46",
    "slug": "humaty",
    "label": "Гумати",
    "title": "Активатор ґрунту та антистресант",
    "description": "Гумати посилюють кореневу систему, поліпшують структуру ґрунту, зв'язують важкі метали. Працюють як «активатор» для решти біопрепаратів у баковій суміші.",
    "image_url": "/inside-bacillus.webp",
    "image_alt": "Гумати",
    "accent_color": "",
    "is_active": true,
    "order": 3,
    "created_at": "2026-06-01T10:27:32.902539+00:00",
    "updated_at": "2026-06-01T10:27:32.902539+00:00"
  }
]